cx_Freeze/__init__.py
cx_Freeze/__main__.py
cx_Freeze/_bytecode.py
cx_Freeze/_compat.py
cx_Freeze/_license.py
cx_Freeze/_pyproject.py
cx_Freeze/_typing.py
cx_Freeze/cli.py
cx_Freeze/common.py
cx_Freeze/darwintools.py
cx_Freeze/dep_parser.py
cx_Freeze/exception.py
cx_Freeze/executable.py
cx_Freeze/finder.py
cx_Freeze/freezer.py
cx_Freeze/module.py
cx_Freeze/setupwriter.py
cx_Freeze/winversioninfo.py
cx_Freeze/command/__init__.py
cx_Freeze/command/_pydialog.py
cx_Freeze/command/bdist_appimage.py
cx_Freeze/command/bdist_deb.py
cx_Freeze/command/bdist_dmg.py
cx_Freeze/command/bdist_mac.py
cx_Freeze/command/bdist_msi.py
cx_Freeze/command/bdist_rpm.py
cx_Freeze/command/build_exe.py
cx_Freeze/command/install.py
cx_Freeze/command/install_exe.py
cx_Freeze/hooks/__init__.py
cx_Freeze/hooks/_anyio_.py
cx_Freeze/hooks/_asyncio_.py
cx_Freeze/hooks/_av_.py
cx_Freeze/hooks/_backports_.py
cx_Freeze/hooks/_clr_.py
cx_Freeze/hooks/_crypto_.py
cx_Freeze/hooks/_cryptodome_.py
cx_Freeze/hooks/_cv2_.py
cx_Freeze/hooks/_easyocr_.py
cx_Freeze/hooks/_fonttools_.py
cx_Freeze/hooks/_gi_.py
cx_Freeze/hooks/_glib_.py
cx_Freeze/hooks/_importlib_.py
cx_Freeze/hooks/_jaraco_.py
cx_Freeze/hooks/_lazy_loader_.py
cx_Freeze/hooks/_matplotlib_.py
cx_Freeze/hooks/_mkl_.py
cx_Freeze/hooks/_multiprocess_.py
cx_Freeze/hooks/_multiprocessing_.py
cx_Freeze/hooks/_numpy_.py
cx_Freeze/hooks/_nvidia_.py
cx_Freeze/hooks/_ortools_.py
cx_Freeze/hooks/_pandas_.py
cx_Freeze/hooks/_pil_.py
cx_Freeze/hooks/_pkg_resources_.py
cx_Freeze/hooks/_pyarrow_.py
cx_Freeze/hooks/_pydantic_.py
cx_Freeze/hooks/_pygments_.py
cx_Freeze/hooks/_pymupdf_.py
cx_Freeze/hooks/_pyparsing_.py
cx_Freeze/hooks/_pyproj_.py
cx_Freeze/hooks/_pytz_.py
cx_Freeze/hooks/_rasterio_.py
cx_Freeze/hooks/_re_.py
cx_Freeze/hooks/_rns_.py
cx_Freeze/hooks/_scipy_.py
cx_Freeze/hooks/_setuptools_.py
cx_Freeze/hooks/_shapely_.py
cx_Freeze/hooks/_skimage_.py
cx_Freeze/hooks/_sklearn_.py
cx_Freeze/hooks/_ssl_.py
cx_Freeze/hooks/_tensorflow_.py
cx_freeze-8.5.2.dist-info/licenses/LICENSE.md
cx_freeze-8.5.2.dist-info/METADATA
cx_freeze-8.5.2.dist-info/WHEEL
cx_freeze-8.5.2.dist-info/entry_points.txt
cx_freeze-8.5.2.dist-info/top_level.txt
cx_freeze-8.5.2.dist-info/RECORD
